src/__init__.py
src/sentiment.py
targimo-0.0.1.dist-info/METADATA
targimo-0.0.1.dist-info/WHEEL
targimo-0.0.1.dist-info/licenses/LICENSE
targimo-0.0.1.dist-info/RECORD
