Metadata-Version: 2.1
Name: targimo
Version: 0.0.1
Summary: Targimo: An Artifical Intelligence Model that Revolutionizes Sentiment Analysis
Project-URL: Homepage, https://github.com/tesseract-ocr/tesseract
Author: Abdulrahman Sinjab, Ahmed Mostafa, Dominic Orlando, Younus Ahmad, Yusuf Morsi, Ali Aliani, Nabhan Sazzad
License-File: LICENSE
Classifier: License :: OSI Approved :: MIT License
Classifier: Operating System :: OS Independent
Classifier: Programming Language :: Python :: 3
Requires-Python: >=3.7
